nnunet_extend/__init__.py
nnunet_extend/dataset_conversion/ADE20K.py
nnunet_extend/dataset_conversion/DRIVE.py
nnunet_extend/dataset_conversion/RoadSegmentation.py
nnunet_extend/dataset_conversion/__init__.py
nnunet_extend/evaluation/evaluate_predictions.py
nnunet_extend/inference/__init__.py
nnunet_extend/inference/custom_inference.py
nnunet_extend/inference/predict_from_raw_data.py
nnunet_extend/network_architecture/DFormer.py
nnunet_extend/network_architecture/LKMUNet.py
nnunet_extend/network_architecture/LightMUNet.py
nnunet_extend/network_architecture/SegMamba.py
nnunet_extend/network_architecture/__init__.py
nnunet_extend/network_architecture/mmseg.py
nnunet_extend/network_architecture/monai_model.py
nnunet_extend/network_architecture/torchvision_model_zoo.py
nnunet_extend/network_architecture/BiFormer/model.py
nnunet_extend/network_architecture/BiFormer/backbones/biformer.py
nnunet_extend/network_architecture/BiFormer/configs/upernet_biformer_base_512.py
nnunet_extend/network_architecture/BiFormer/configs/upernet_biformer_small_512.py
nnunet_extend/network_architecture/CCNet/model.py
nnunet_extend/network_architecture/CCNet/configs/ccnet_r101-d8.py
nnunet_extend/network_architecture/CCNet/configs/ccnet_r50-d8.py
nnunet_extend/network_architecture/CoTr/CNNBackbone.py
nnunet_extend/network_architecture/CoTr/ResTranUnet.py
nnunet_extend/network_architecture/CoTr/__init__.py
nnunet_extend/network_architecture/CoTr/neural_network.py
nnunet_extend/network_architecture/CoTr/DeTrans/DeformableTrans.py
nnunet_extend/network_architecture/CoTr/DeTrans/position_encoding.py
nnunet_extend/network_architecture/CoTr/DeTrans/ops/functions/ms_deform_attn_func.py
nnunet_extend/network_architecture/CoTr/DeTrans/ops/modules/__init__.py
nnunet_extend/network_architecture/CoTr/DeTrans/ops/modules/ms_deform_attn.py
nnunet_extend/network_architecture/DAMamba/model.py
nnunet_extend/network_architecture/DAMamba/backbones/DAMamba.py
nnunet_extend-2025.4.24.dist-info/licenses/LICENSE
nnunet_extend-2025.4.24.dist-info/METADATA
nnunet_extend-2025.4.24.dist-info/WHEEL
nnunet_extend-2025.4.24.dist-info/entry_points.txt
nnunet_extend-2025.4.24.dist-info/top_level.txt
nnunet_extend-2025.4.24.dist-info/RECORD
