Metadata-Version: 2.4
Name: nnunet_extend
Version: 2025.4.24
Summary: nnunet extend
Author-email: jiang yan <1900812927@qq.com>
License: MIT License
Project-URL: homepage, https://gitee.com/Eason596/nnunet_extend
Project-URL: repository, https://gitee.com/Eason596/nnunet_extend
Keywords: deep learning,image segmentation,semantic segmentation,medical image analysis,medical image segmentation,nnU-Net,nnunet
Requires-Python: >=3.10
License-File: LICENSE
Requires-Dist: torch>=2.6.0
Requires-Dist: nnunetv2>=2.6.0
Requires-Dist: monai>=1.4.0
Requires-Dist: mmengine>=0.10.6
Requires-Dist: ml_collections
Requires-Dist: timm
Requires-Dist: fairscale
Requires-Dist: ftfy
Provides-Extra: dev
Requires-Dist: black; extra == "dev"
Requires-Dist: ruff; extra == "dev"
Requires-Dist: pre-commit; extra == "dev"
Dynamic: license-file
